agegrid/__init__.py
agegrid/automatic_age_grid_seeding.py
agegrid/reconstruct_by_topologies.py
agegrid/run_paleo_age_grids.py
gprm/GPlatesReconstructionModel.py
gprm/__init__.py
gprm/datasets/Geology.py
gprm/datasets/Paleogeography.py
gprm/datasets/Reconstructions.py
gprm/datasets/Rocks.py
gprm/datasets/Seafloor.py
gprm/datasets/Strat.py
gprm/datasets/Zircons.py
gprm/datasets/__init__.py
gprm/utils/__init__.py
gprm/utils/create_gpml.py
gprm/utils/deformation.py
gprm/utils/fileio.py
gprm/utils/geometry.py
gprm/utils/inpaint.py
gprm/utils/paleogeography.py
gprm/utils/paleotopography.py
gprm/utils/pca_utils.py
gprm/utils/platetree.py
gprm/utils/pmag.py
gprm/utils/proximity.py
gprm/utils/raster.py
gprm/utils/rotation.py
gprm/utils/spatial.py
gprm/utils/sphere.py
gprm/utils/vector.py
gprm/utils/web_service.py
gprm/utils/wrapping_tools.py
paleo_age_grids-1.2.1.dist-info/licenses/LICENSE
paleo_age_grids-1.2.1.dist-info/METADATA
paleo_age_grids-1.2.1.dist-info/WHEEL
paleo_age_grids-1.2.1.dist-info/top_level.txt
paleo_age_grids-1.2.1.dist-info/RECORD
