Metadata-Version: 2.4
Name: paleo-age-grids
Version: 1.2.1
Summary: Code for reconstructing seafloor age distributions from GPlates full-plate tectonic reconstructions.
Author-email: Lucas Amion <lamion@dcc.uchile.cl>
Maintainer-email: Lucas Amion <lamion@dcc.uchile.cl>
License:                     GNU GENERAL PUBLIC LICENSE
Project-URL: Source Code, https://github.com/LucasAmion/agegrid
Requires-Python: >=3.8
License-File: LICENSE
Requires-Dist: numpy
Requires-Dist: xarray
Requires-Dist: scikit-image
Requires-Dist: astropy-healpix
Requires-Dist: pygmt
Requires-Dist: pygplates
Requires-Dist: PlateTectonicTools
Requires-Dist: joblib
Dynamic: license-file
